itkdb/__init__.py
itkdb/_version.py
itkdb/_version.pyi
itkdb/client.py
itkdb/commandline.py
itkdb/core.py
itkdb/eos.py
itkdb/exceptions.py
itkdb/py.typed
itkdb/responses.py
itkdb/typing.py
itkdb/utils.py
itkdb/caching/__init__.py
itkdb/caching/adapter.py
itkdb/caching/controller.py
itkdb/caching/utils.py
itkdb/data/1x1.jpg
itkdb/data/1x1.sh
itkdb/data/CERN_chain.pem
itkdb/data/README.md
itkdb/data/__init__.py
itkdb/data/tiny.root
itkdb/models/__init__.py
itkdb/models/component.py
itkdb/models/file.py
itkdb/models/institution.py
itkdb/settings/__init__.py
itkdb/settings/base.py
itkdb-0.6.17.dist-info/METADATA
itkdb-0.6.17.dist-info/WHEEL
itkdb-0.6.17.dist-info/entry_points.txt
itkdb-0.6.17.dist-info/licenses/COPYING
itkdb-0.6.17.dist-info/licenses/LICENSE
itkdb-0.6.17.dist-info/RECORD
