Metadata-Version: 2.4
Name: itkdb
Version: 0.6.17
Summary: Python wrapper to interface with ITk DB.
Project-URL: Documentation, https://itkdb.docs.cern.ch/0.6/
Project-URL: Homepage, https://gitlab.cern.ch/atlas-itk/sw/db/itkdb
Project-URL: Bug Tracker, https://gitlab.cern.ch/atlas-itk/sw/db/itkdb/issues
Project-URL: Source, https://gitlab.cern.ch/atlas-itk/sw/db/itkdb
Author-email: Giordon Stark <kratsg@gmail.com>
Maintainer-email: Giordon Stark <kratsg@gmail.com>
License-File: COPYING
License-File: LICENSE
Classifier: Development Status :: 1 - Planning
Classifier: Intended Audience :: Developers
Classifier: Intended Audience :: Science/Research
Classifier: License :: OSI Approved :: BSD License
Classifier: License :: OSI Approved :: GNU General Public License v3 (GPLv3)
Classifier: Operating System :: OS Independent
Classifier: Programming Language :: Python
Classifier: Programming Language :: Python :: 3
Classifier: Programming Language :: Python :: 3 :: Only
Classifier: Programming Language :: Python :: 3.8
Classifier: Programming Language :: Python :: 3.9
Classifier: Programming Language :: Python :: 3.10
Classifier: Programming Language :: Python :: 3.11
Classifier: Topic :: Scientific/Engineering
Requires-Python: >=3.8
Requires-Dist: attrs
Requires-Dist: cachecontrol[filecache]
Requires-Dist: certifi
Requires-Dist: click; python_version >= '3.10'
Requires-Dist: click<8.2; python_version < '3.10'
Requires-Dist: importlib-resources; python_version < '3.9'
Requires-Dist: pylibmagic; platform_system != 'Windows'
Requires-Dist: python-dotenv
Requires-Dist: python-jose
Requires-Dist: python-magic-bin; platform_system == 'Windows'
Requires-Dist: python-magic; platform_system != 'Windows'
Requires-Dist: requests>=2.0
Requires-Dist: simple-settings
Requires-Dist: typing-extensions>=4.0; python_version < '3.11'
Requires-Dist: urllib3<2,>=1.26.20; 'el7.x86_64' in platform_release
Requires-Dist: urllib3>=1.26.20
Provides-Extra: contrib
Requires-Dist: html2text; extra == 'contrib'
Provides-Extra: eos
Requires-Dist: pycurl; extra == 'eos'
